[
  {
    "id": 7,
    "course_id": 7,
    "year": 2026,
    "round_label": "2026년 1·2·3회차",
    "organizer": "한국산업인력공단",
    "subjects_json": "[{\"round\":\"필기(공통)\",\"name\":\"전기자기학\",\"count\":\"20문항\",\"time\":\"교시별 30분\"},{\"round\":\"필기(공통)\",\"name\":\"전력공학\",\"count\":\"20문항\",\"time\":\"교시별 30분\"},{\"round\":\"필기(공통)\",\"name\":\"전기기기\",\"count\":\"20문항\",\"time\":\"교시별 30분\"},{\"round\":\"필기(공통)\",\"name\":\"회로이론 및 제어공학\",\"count\":\"20문항\",\"time\":\"교시별 30분\"},{\"round\":\"필기(공통)\",\"name\":\"전기설비기술기준\",\"count\":\"20문항\",\"time\":\"교시별 30분\"},{\"round\":\"실기\",\"name\":\"전기설비설계 및 관리 (필답형)\",\"count\":\"주관식\",\"time\":\"2시간 30분\"}]",
    "exam_fee": "필기 19,400원 / 실기 20,800원",
    "written_reg_start": "1회: 2026.01.12 / 2회: 2026.04.20 / 3회: 2026.07.20",
    "written_reg_end": "1회: 2026.01.15 / 2회: 2026.04.23 / 3회: 2026.07.23",
    "written_exam_date": "1회: 2026.01.30~03.03 / 2회: 2026.05.09~05.29 / 3회: 2026.08.07~09.01",
    "written_result_date": "1회: 2026.03.11 / 2회: 2026.06.10 / 3회: 2026.09.09",
    "practical_reg_start": "1회: 2026.03.23 / 2회: 2026.06.22 / 3회: 2026.09.21",
    "practical_reg_end": "1회: 2026.03.26 / 2회: 2026.06.25 / 3회: 2026.09.23",
    "practical_exam_date": "1회: 2026.04.18~05.06 / 2회: 2026.07.18~08.05 / 3회: 2026.10.24~11.13",
    "practical_result_date": "1회: 2026.06.05 / 2회: 2026.09.04 / 3회: 미정",
    "notes": "• 필기: 각 과목 40점 이상 + 평균 60점 이상\n• 실기: 60점 이상 합격\n• 필기 합격 후 2년간 필기 면제 (동일종목 실기에 한함)\n• 학력 또는 경력요건 있음 (관련학과 졸업 등)",
    "source_url": "https://www.q-net.or.kr",
    "data_source": "manual",
    "pass_rates_json": "[{\"year\": \"2024\", \"round\": \"필기\", \"applicants\": \"57,417명\", \"passed\": \"15,005명\", \"rate\": \"26.1%\"}, {\"year\": \"2024\", \"round\": \"실기\", \"applicants\": \"27,063명\", \"passed\": \"10,115명\", \"rate\": \"37.4%\"}, {\"year\": \"2023\", \"round\": \"필기\", \"applicants\": \"51,630명\", \"passed\": \"11,477명\", \"rate\": \"22.2%\"}, {\"year\": \"2023\", \"round\": \"실기\", \"applicants\": \"23,643명\", \"passed\": \"8,774명\", \"rate\": \"37.1%\"}, {\"year\": \"2022\", \"round\": \"필기\", \"applicants\": \"52,187명\", \"passed\": \"11,652명\", \"rate\": \"22.3%\"}, {\"year\": \"2022\", \"round\": \"실기\", \"applicants\": \"32,640명\", \"passed\": \"12,901명\", \"rate\": \"39.5%\"}, {\"year\": \"2021\", \"round\": \"필기\", \"applicants\": \"60,499명\", \"passed\": \"13,412명\", \"rate\": \"22.2%\"}, {\"year\": \"2021\", \"round\": \"실기\", \"applicants\": \"33,816명\", \"passed\": \"9,916명\", \"rate\": \"29.3%\"}, {\"year\": \"2020\", \"round\": \"필기\", \"applicants\": \"56,376명\", \"passed\": \"15,970명\", \"rate\": \"28.3%\"}, {\"year\": \"2020\", \"round\": \"실기\", \"applicants\": \"42,416명\", \"passed\": \"7,151명\", \"rate\": \"16.9%\"}]"
  }
]